evercolab/__init__.py
evercolab/add.py
evercolab/ever.py
evercolab/extras/__init__.py
evercolab/extras/request.py
evercolab-1.0.5.dist-info/METADATA
evercolab-1.0.5.dist-info/WHEEL
evercolab-1.0.5.dist-info/top_level.txt
evercolab-1.0.5.dist-info/RECORD
