Metadata-Version: 2.1
Name: evercolab
Version: 1.0.5
Summary: Data sharing between projects
Home-page: UNKNOWN
Author: Afendin Ilya
Author-email: afendin.ilya@gmail.com
License: UNKNOWN
Keywords: python,colabarative
Platform: UNKNOWN
Classifier: Development Status :: 3 - Alpha
Classifier: Intended Audience :: Education
Classifier: Programming Language :: Python :: 2
Classifier: Programming Language :: Python :: 3
Classifier: Operating System :: MacOS :: MacOS X
Classifier: Operating System :: Microsoft :: Windows
